phunky/__init__.py
phunky/classes.py
phunky/decorators.py
phunky/functions.py
phunky/logging.json
phunky/main.py
phunky/pipelines.py
phunky-0.3.dist-info/METADATA
phunky-0.3.dist-info/WHEEL
phunky-0.3.dist-info/top_level.txt
phunky-0.3.dist-info/RECORD
